[
  {
    "part": "Flutter",
    "start": 10250,
    "end": 10806
  },
  {
    "part": "是",
    "start": 10897,
    "end": 11090
  },
  {
    "part": "Google",
    "start": 11102,
    "end": 11420
  },
  {
    "part": "的",
    "start": 11420,
    "end": 11499
  },
  {
    "part": "跨平台",
    "start": 11522,
    "end": 11965
  },
  {
    "part": "框架。",
    "start": 11977,
    "end": 12443
  },
  {
    "part": "Dart",
    "start": 12965,
    "end": 13306
  },
  {
    "part": "语言",
    "start": 13306,
    "end": 13602
  },
  {
    "part": "编写，",
    "start": 13613,
    "end": 14079
  },
  {
    "part": "编译",
    "start": 14340,
    "end": 14613
  },
  {
    "part": "为",
    "start": 14613,
    "end": 14772
  },
  {
    "part": "原生",
    "start": 14795,
    "end": 15147
  },
  {
    "part": "代码，",
    "start": 15159,
    "end": 15568
  },
  {
    "part": "性能",
    "start": 15818,
    "end": 16147
  },
  {
    "part": "接近",
    "start": 16159,
    "end": 16499
  },
  {
    "part": "原生",
    "start": 16522,
    "end": 16829
  },
  {
    "part": "应用。",
    "start": 16840,
    "end": 17238
  },
  {
    "part": "ClawChat",
    "start": 17761,
    "end": 18238
  },
  {
    "part": "选择",
    "start": 18250,
    "end": 18761
  },
  {
    "part": "Flutter",
    "start": 18863,
    "end": 19318
  },
  {
    "part": "是",
    "start": 19329,
    "end": 19454
  },
  {
    "part": "因为",
    "start": 19454,
    "end": 19852
  },
  {
    "part": "它",
    "start": 19943,
    "end": 20079
  },
  {
    "part": "能",
    "start": 20090,
    "end": 20204
  },
  {
    "part": "用",
    "start": 20204,
    "end": 20352
  },
  {
    "part": "最少",
    "start": 20375,
    "end": 20727
  },
  {
    "part": "的",
    "start": 20727,
    "end": 20806
  },
  {
    "part": "代码",
    "start": 20818,
    "end": 21227
  },
  {
    "part": "覆盖",
    "start": 21318,
    "end": 21636
  },
  {
    "part": "最多",
    "start": 21659,
    "end": 21999
  },
  {
    "part": "的",
    "start": 22000,
    "end": 22079
  },
  {
    "part": "平台。",
    "start": 22090,
    "end": 22556
  }
]