[
  {
    "part": "总结",
    "start": 53852,
    "end": 54227
  },
  {
    "part": "一下：",
    "start": 54238,
    "end": 54602
  },
  {
    "part": "Saga",
    "start": 54897,
    "end": 55215
  },
  {
    "part": "模式",
    "start": 55227,
    "end": 55693
  },
  {
    "part": "让",
    "start": 55772,
    "end": 55954
  },
  {
    "part": "多",
    "start": 55954,
    "end": 56102
  },
  {
    "part": "服务",
    "start": 56113,
    "end": 56386
  },
  {
    "part": "编排",
    "start": 56397,
    "end": 56840
  },
  {
    "part": "变得",
    "start": 56863,
    "end": 57068
  },
  {
    "part": "可靠。",
    "start": 57079,
    "end": 57556
  },
  {
    "part": "创建",
    "start": 58079,
    "end": 58465
  },
  {
    "part": "失败",
    "start": 58477,
    "end": 58818
  },
  {
    "part": "不",
    "start": 58840,
    "end": 58943
  },
  {
    "part": "留",
    "start": 58943,
    "end": 59068
  },
  {
    "part": "脏",
    "start": 59068,
    "end": 59238
  },
  {
    "part": "数据，",
    "start": 59250,
    "end": 59693
  },
  {
    "part": "用户",
    "start": 59977,
    "end": 60284
  },
  {
    "part": "看到",
    "start": 60295,
    "end": 60693
  },
  {
    "part": "的",
    "start": 60693,
    "end": 60909
  },
  {
    "part": "就",
    "start": 61000,
    "end": 61136
  },
  {
    "part": "是",
    "start": 61136,
    "end": 61238
  },
  {
    "part": "成功",
    "start": 61250,
    "end": 61625
  },
  {
    "part": "或",
    "start": 61647,
    "end": 61761
  },
  {
    "part": "失败，",
    "start": 61772,
    "end": 62170
  },
  {
    "part": "没有",
    "start": 62409,
    "end": 62659
  },
  {
    "part": "中间态。",
    "start": 62670,
    "end": 63261
  }
]