[
  {
    "part": "nginx",
    "start": 36000,
    "end": 36386
  },
  {
    "part": "做",
    "start": 36386,
    "end": 36590
  },
  {
    "part": "统一",
    "start": 36602,
    "end": 36931
  },
  {
    "part": "入口",
    "start": 36943,
    "end": 37386
  },
  {
    "part": "和",
    "start": 37477,
    "end": 37624
  },
  {
    "part": "反向",
    "start": 37636,
    "end": 38011
  },
  {
    "part": "代理。",
    "start": 38022,
    "end": 38409
  },
  {
    "part": "所有",
    "start": 38931,
    "end": 39454
  },
  {
    "part": "API",
    "start": 39545,
    "end": 40068
  },
  {
    "part": "通过",
    "start": 40079,
    "end": 40420
  },
  {
    "part": "路径",
    "start": 40443,
    "end": 40715
  },
  {
    "part": "前缀",
    "start": 40727,
    "end": 41215
  },
  {
    "part": "路",
    "start": 41306,
    "end": 41420
  },
  {
    "part": "由到",
    "start": 41420,
    "end": 41738
  },
  {
    "part": "对应",
    "start": 41761,
    "end": 42045
  },
  {
    "part": "服务，",
    "start": 42056,
    "end": 42465
  },
  {
    "part": "Flutter ",
    "start": 42761,
    "end": 43136
  },
  {
    "part": "Web",
    "start": 43147,
    "end": 43420
  },
  {
    "part": "静态",
    "start": 43420,
    "end": 43715
  },
  {
    "part": "文件",
    "start": 43727,
    "end": 44181
  },
  {
    "part": "也",
    "start": 44272,
    "end": 44397
  },
  {
    "part": "通过",
    "start": 44397,
    "end": 44715
  },
  {
    "part": "nginx",
    "start": 44738,
    "end": 45056
  },
  {
    "part": "提供。",
    "start": 45068,
    "end": 45477
  },
  {
    "part": "SSL",
    "start": 46000,
    "end": 46693
  },
  {
    "part": "证书、",
    "start": 46704,
    "end": 47170
  },
  {
    "part": "CORS、",
    "start": 47340,
    "end": 47818
  },
  {
    "part": "安全",
    "start": 48045,
    "end": 48386
  },
  {
    "part": "头全部",
    "start": 48397,
    "end": 48909
  },
  {
    "part": "在",
    "start": 48920,
    "end": 49102
  },
  {
    "part": "nginx",
    "start": 49125,
    "end": 49511
  },
  {
    "part": "层",
    "start": 49511,
    "end": 49704
  },
  {
    "part": "处理。",
    "start": 49715,
    "end": 50079
  }
]