[
  {
    "part": "Agent",
    "start": 8954,
    "end": 9363
  },
  {
    "part": "写入",
    "start": 9375,
    "end": 9829
  },
  {
    "part": "MEMORY",
    "start": 9920,
    "end": 10318
  },
  {
    "part": "点",
    "start": 10318,
    "end": 10499
  },
  {
    "part": "MD",
    "start": 10511,
    "end": 10852
  },
  {
    "part": "后，",
    "start": 10852,
    "end": 11124
  },
  {
    "part": "记忆",
    "start": 11375,
    "end": 11659
  },
  {
    "part": "自动",
    "start": 11681,
    "end": 11931
  },
  {
    "part": "热",
    "start": 11943,
    "end": 12079
  },
  {
    "part": "更新，",
    "start": 12079,
    "end": 12511
  },
  {
    "part": "不",
    "start": 12704,
    "end": 12829
  },
  {
    "part": "需要",
    "start": 12829,
    "end": 13090
  },
  {
    "part": "重启。",
    "start": 13102,
    "end": 13602
  },
  {
    "part": "下",
    "start": 14125,
    "end": 14386
  },
  {
    "part": "一",
    "start": 14386,
    "end": 14465
  },
  {
    "part": "轮",
    "start": 14465,
    "end": 14602
  },
  {
    "part": "对话",
    "start": 14613,
    "end": 15034
  },
  {
    "part": "就",
    "start": 15125,
    "end": 15250
  },
  {
    "part": "能",
    "start": 15250,
    "end": 15340
  },
  {
    "part": "用到",
    "start": 15352,
    "end": 15613
  },
  {
    "part": "新",
    "start": 15636,
    "end": 15886
  },
  {
    "part": "记忆。",
    "start": 15886,
    "end": 16295
  },
  {
    "part": "未来",
    "start": 16806,
    "end": 17238
  },
  {
    "part": "可",
    "start": 17261,
    "end": 17397
  },
  {
    "part": "扩展",
    "start": 17409,
    "end": 17772
  },
  {
    "part": "为",
    "start": 17772,
    "end": 17988
  },
  {
    "part": "向量",
    "start": 18011,
    "end": 18340
  },
  {
    "part": "数据库",
    "start": 18352,
    "end": 18806
  },
  {
    "part": "存储。",
    "start": 18818,
    "end": 19340
  }
]