[
  {
    "part": "数据流。",
    "start": 62886,
    "end": 63602
  },
  {
    "part": "用户",
    "start": 64113,
    "end": 64397
  },
  {
    "part": "消息",
    "start": 64409,
    "end": 64897
  },
  {
    "part": "通过",
    "start": 64909,
    "end": 65284
  },
  {
    "part": "WebSocket",
    "start": 65306,
    "end": 66022
  },
  {
    "part": "到达",
    "start": 66045,
    "end": 66318
  },
  {
    "part": "网关，",
    "start": 66329,
    "end": 66806
  },
  {
    "part": "网关路",
    "start": 67022,
    "end": 67499
  },
  {
    "part": "由到",
    "start": 67500,
    "end": 67784
  },
  {
    "part": "对应",
    "start": 67795,
    "end": 68113
  },
  {
    "part": "的",
    "start": 68113,
    "end": 68204
  },
  {
    "part": "Pod。",
    "start": 68204,
    "end": 68568
  },
  {
    "part": "Pod",
    "start": 69079,
    "end": 69374
  },
  {
    "part": "里",
    "start": 69375,
    "end": 69500
  },
  {
    "part": "的",
    "start": 69500,
    "end": 69659
  },
  {
    "part": "agent-core",
    "start": 69681,
    "end": 70284
  },
  {
    "part": "调大",
    "start": 70295,
    "end": 70636
  },
  {
    "part": "模型",
    "start": 70647,
    "end": 71102
  },
  {
    "part": "API，",
    "start": 71193,
    "end": 71772
  },
  {
    "part": "执行",
    "start": 71965,
    "end": 72284
  },
  {
    "part": "工具，",
    "start": 72295,
    "end": 72727
  },
  {
    "part": "返回",
    "start": 72931,
    "end": 73261
  },
  {
    "part": "结果。",
    "start": 73272,
    "end": 73727
  },
  {
    "part": "聊天",
    "start": 74250,
    "end": 74647
  },
  {
    "part": "记录",
    "start": 74659,
    "end": 74897
  },
  {
    "part": "存",
    "start": 74897,
    "end": 75090
  },
  {
    "part": "数据库，",
    "start": 75102,
    "end": 75659
  },
  {
    "part": "镜像存",
    "start": 75897,
    "end": 76590
  },
  {
    "part": "Registry。",
    "start": 76670,
    "end": 77340
  }
]