[
  {
    "part": "总结",
    "start": 128693,
    "end": 129079
  },
  {
    "part": "一下：",
    "start": 129090,
    "end": 129465
  },
  {
    "part": "三",
    "start": 129772,
    "end": 129977
  },
  {
    "part": "层",
    "start": 129977,
    "end": 130124
  },
  {
    "part": "架构，",
    "start": 130136,
    "end": 130568
  },
  {
    "part": "会话",
    "start": 130829,
    "end": 131136
  },
  {
    "part": "层",
    "start": 131136,
    "end": 131318
  },
  {
    "part": "保",
    "start": 131318,
    "end": 131465
  },
  {
    "part": "完整",
    "start": 131477,
    "end": 131795
  },
  {
    "part": "日志，",
    "start": 131806,
    "end": 132227
  },
  {
    "part": "工作",
    "start": 132545,
    "end": 132829
  },
  {
    "part": "空间",
    "start": 132840,
    "end": 133318
  },
  {
    "part": "层存",
    "start": 133409,
    "end": 133795
  },
  {
    "part": "人类",
    "start": 133806,
    "end": 134193
  },
  {
    "part": "可",
    "start": 134215,
    "end": 134374
  },
  {
    "part": "读",
    "start": 134375,
    "end": 134534
  },
  {
    "part": "笔记，",
    "start": 134545,
    "end": 135011
  },
  {
    "part": "向",
    "start": 135227,
    "end": 135454
  },
  {
    "part": "量层",
    "start": 135465,
    "end": 135829
  },
  {
    "part": "支持",
    "start": 135840,
    "end": 136249
  },
  {
    "part": "语义",
    "start": 136272,
    "end": 136545
  },
  {
    "part": "搜索。",
    "start": 136556,
    "end": 137045
  },
  {
    "part": "备份",
    "start": 137568,
    "end": 137931
  },
  {
    "part": "推荐",
    "start": 137954,
    "end": 138261
  },
  {
    "part": "打包",
    "start": 138272,
    "end": 138704
  },
  {
    "part": "Markdown",
    "start": 138795,
    "end": 139261
  },
  {
    "part": "文件，",
    "start": 139272,
    "end": 139704
  },
  {
    "part": "轻量",
    "start": 139920,
    "end": 140295
  },
  {
    "part": "且",
    "start": 140318,
    "end": 140443
  },
  {
    "part": "通用。",
    "start": 140454,
    "end": 140897
  },
  {
    "part": "Agent",
    "start": 141420,
    "end": 141874
  },
  {
    "part": "的",
    "start": 141875,
    "end": 141988
  },
  {
    "part": "记忆",
    "start": 142000,
    "end": 142454
  },
  {
    "part": "就",
    "start": 142545,
    "end": 142704
  },
  {
    "part": "是",
    "start": 142704,
    "end": 142795
  },
  {
    "part": "它",
    "start": 142806,
    "end": 142943
  },
  {
    "part": "的",
    "start": 142943,
    "end": 143034
  },
  {
    "part": "经验，",
    "start": 143045,
    "end": 143499
  },
  {
    "part": "值得",
    "start": 143715,
    "end": 143988
  },
  {
    "part": "好好",
    "start": 144011,
    "end": 144352
  },
  {
    "part": "保管。",
    "start": 144363,
    "end": 144795
  }
]