[
  {
    "part": "setup",
    "start": 29545,
    "end": 30011
  },
  {
    "part": "方法",
    "start": 30022,
    "end": 30363
  },
  {
    "part": "是",
    "start": 30363,
    "end": 30659
  },
  {
    "part": "启动",
    "start": 30750,
    "end": 31102
  },
  {
    "part": "入口。",
    "start": 31113,
    "end": 31545
  },
  {
    "part": "先",
    "start": 32068,
    "end": 32329
  },
  {
    "part": "调",
    "start": 32329,
    "end": 32534
  },
  {
    "part": "loadTasks",
    "start": 32534,
    "end": 33159
  },
  {
    "part": "读取",
    "start": 33170,
    "end": 33636
  },
  {
    "part": "HEARTBEAT.",
    "start": 33727,
    "end": 34363
  },
  {
    "part": "md",
    "start": 34590,
    "end": 35056
  },
  {
    "part": "并解",
    "start": 35147,
    "end": 35465
  },
  {
    "part": "析",
    "start": 35465,
    "end": 35659
  },
  {
    "part": "任务",
    "start": 35681,
    "end": 35886
  },
  {
    "part": "列表，",
    "start": 35897,
    "end": 36340
  },
  {
    "part": "然后",
    "start": 36625,
    "end": 36920
  },
  {
    "part": "用",
    "start": 36931,
    "end": 37181
  },
  {
    "part": "fs.",
    "start": 37204,
    "end": 37602
  },
  {
    "part": "watch",
    "start": 37659,
    "end": 37965
  },
  {
    "part": "监听",
    "start": 37988,
    "end": 38295
  },
  {
    "part": "文件",
    "start": 38306,
    "end": 38613
  },
  {
    "part": "变化",
    "start": 38625,
    "end": 39079
  },
  {
    "part": "实现",
    "start": 39170,
    "end": 39522
  },
  {
    "part": "热重载。",
    "start": 39545,
    "end": 40113
  },
  {
    "part": "同时",
    "start": 40636,
    "end": 41136
  },
  {
    "part": "启动",
    "start": 41227,
    "end": 41522
  },
  {
    "part": "一个",
    "start": 41534,
    "end": 41704
  },
  {
    "part": "60秒",
    "start": 41727,
    "end": 42147
  },
  {
    "part": "间隔",
    "start": 42159,
    "end": 42545
  },
  {
    "part": "的",
    "start": 42545,
    "end": 42761
  },
  {
    "part": "setInterval",
    "start": 42852,
    "end": 43590
  },
  {
    "part": "做",
    "start": 43681,
    "end": 43886
  },
  {
    "part": "cron",
    "start": 43897,
    "end": 44193
  },
  {
    "part": "轮询，",
    "start": 44193,
    "end": 44693
  },
  {
    "part": "触发",
    "start": 44909,
    "end": 45272
  },
  {
    "part": "时",
    "start": 45272,
    "end": 45590
  },
  {
    "part": "调用",
    "start": 45681,
    "end": 46090
  },
  {
    "part": "createEvent",
    "start": 46113,
    "end": 46920
  },
  {
    "part": "推送",
    "start": 47011,
    "end": 47420
  },
  {
    "part": "timer",
    "start": 47443,
    "end": 47738
  },
  {
    "part": "事件",
    "start": 47750,
    "end": 48113
  },
  {
    "part": "到",
    "start": 48125,
    "end": 48375
  },
  {
    "part": "EventLoop。",
    "start": 48465,
    "end": 49181
  }
]